toobj/__init__.py
toobj-0.0.1.dist-info/LICENSE
toobj-0.0.1.dist-info/METADATA
toobj-0.0.1.dist-info/WHEEL
toobj-0.0.1.dist-info/top_level.txt
toobj-0.0.1.dist-info/RECORD
