Metadata-Version: 2.1
Name: toobj
Version: 0.0.1
Summary: Python package that transforms flat or nested dictionaries into objects.
Home-page: https://github.com/Jaldekoa/toobj
Author: Jon Aldekoa
Author-email: jaldekoa@gmail.com
Platform: Any
Classifier: Programming Language :: Python :: 3
Classifier: Operating System :: OS Independent
Classifier: License :: OSI Approved :: GNU General Public License v3 (GPLv3)
License-File: LICENSE
Requires-Dist: setuptools
Requires-Dist: pytest
